LICENSE
README.md
setup.py
PySquared.egg-info/PKG-INFO
PySquared.egg-info/SOURCES.txt
PySquared.egg-info/dependency_links.txt
PySquared.egg-info/requires.txt
PySquared.egg-info/top_level.txt
pysquared/__init__.py
pysquared/sidebar_ui.py
pysquared/utils.py
pysquared/dataitems/__init__.py
pysquared/dataitems/abstract_data.py
pysquared/dataitems/abstract_path.py
pysquared/dataitems/decorators.py
pysquared/dataitems/directories.py
pysquared/dataitems/file.py
pysquared/dataitems/keynames_layers.py
pysquared/dataitems/object.py
pysquared/planner/__init__.py
pysquared/planner/accessgraph.py
pysquared/planner/pathselectors.py
pysquared/planner/transform_concrete.py
pysquared/planner/transform_executor.py
pysquared/planner/transform_utils.py
pysquared/planner/transformator.py
pysquared/storage/__init__.py
pysquared/storage/storage.py
pysquared/threadmanager/__init__.py
pysquared/threadmanager/manager.py
pysquared/transforms/__init__.py
pysquared/transforms/abstract_transform.py
pysquared/transforms/transform_templates.py
pysquared/worker/__init__.py
pysquared/worker/worker_thread.py
pysquared/workflow/__init__.py
pysquared/workflow/instruction.py
pysquared/workflow/instruction_factories.py
pysquared/workflow/stack.py
pysquared/workflow/workflow.py