Metadata-Version: 2.1
Name: PySquared
Version: 0.0.3
Summary: Pipeline automation framework for Python
Author: Nikolai Krivoshchapov
Author-email: nikolai.krivoshchapov@gmail.com
License: MIT
Project-URL: GitLab page, https://gitlab.com/knvvv/pysquared
Project-URL: PyPi release, https://pypi.org/project/pysquared/
License-File: LICENSE
